aztex-0.0.3.dist-info/entry_points.txt
aztex-0.0.3.dist-info/DESCRIPTION.rst
aztex-0.0.3.dist-info/WHEEL
aztex-0.0.3.dist-info/top_level.txt
aztex-0.0.3.dist-info/METADATA
aztex-0.0.3.dist-info/metadata.json
aztex-0.0.3.dist-info/RECORD
aztex/TestSuiteRunner.py
aztex/AztexCompiler.py
aztex/Equation.py
aztex/InternalRepresentation.py
aztex/Regex.py
aztex/PDFViewer.py
aztex/AztexRunnerGUI.py
aztex/Parser.py
aztex/AztexRunnerText.py
aztex/main.py
aztex/GenericOutput.py
aztex/aztex.py
aztex/Tokenizer.py
aztex/Element.py
aztex/LatexOutput.py
aztex/Matcher.py
aztex/__init__.py
