Metadata-Version: 2.0
Name: aztex
Version: 0.0.3
Summary: A zippy markdown to latex compiler
Home-page: https://github.com/thuctran289/aztex
Author: Thuc Tran, Jordan Van Duyne, Isaac Getto
Author-email: isaac.getto@gmail.com
License: MIT
Keywords: aztex markdown latex pdf document
Platform: any
Classifier: Development Status :: 3 - Alpha
Classifier: Intended Audience :: End Users/Desktop
Classifier: Intended Audience :: Education
Classifier: Topic :: Education
Classifier: Topic :: Office/Business
Classifier: Topic :: Printing
Classifier: Topic :: Software Development :: Compilers
Classifier: Topic :: Text Editors
Classifier: Topic :: Text Editors :: Text Processing
Classifier: Topic :: Text Editors :: Word Processors
Classifier: Topic :: Text Processing :: Markup
Classifier: Topic :: Text Processing :: Markup :: LaTeX
Classifier: License :: OSI Approved :: MIT License
Classifier: Programming Language :: Python :: 2
Classifier: Programming Language :: Python :: 2.6
Classifier: Programming Language :: Python :: 2.7
Classifier: Programming Language :: Python :: 3
Classifier: Programming Language :: Python :: 3.2
Classifier: Programming Language :: Python :: 3.3
Classifier: Programming Language :: Python :: 3.4
